{
  "type": "FeatureCollection",
  "features": [
    {
      "type": "Feature",
      "geometry": {
        "type": "Point",
        "coordinates": [
          2.34,
          48.86,
          30
        ]
      },
      "properties": {
        "location": {
          "name": "Paris"
        },
        "requestPointDistance": 1184.0156,
        "modelRunDate": "2022-06-04T19:00Z",
        "timeSeries": [
          {
            "time": "2022-06-04T18:00Z",
            "maxScreenAirTemp": 27.09,
            "minScreenAirTemp": 25.52,
            "max10mWindGust": 5.83,
            "significantWeatherCode": 14,
            "totalPrecipAmount": 2.55,
            "totalSnowAmount": 0,
            "windSpeed10m": 1.78,
            "windDirectionFrom10m": 88,
            "windGustSpeed10m": 4.91,
            "visibility": 22169,
            "mslp": 101490,
            "screenRelativeHumidity": 58.15,
            "feelsLikeTemp": 26.53,
            "uvIndex": 1,
            "probOfPrecipitation": 65,
            "probOfSnow": 0,
            "probOfHeavySnow": 0,
            "probOfRain": 65,
            "probOfHeavyRain": 63,
            "probOfHail": 13,
            "probOfSferics": 16
          },
          {
            "time": "2022-06-04T21:00Z",
            "maxScreenAirTemp": 25.57,
            "minScreenAirTemp": 22.3,
            "max10mWindGust": 4.93,
            "significantWeatherCode": 13,
            "totalPrecipAmount": 7.21,
            "totalSnowAmount": 0,
            "windSpeed10m": 2.22,
            "windDirectionFrom10m": 317,
            "windGustSpeed10m": 4.93,
            "visibility": 11417,
            "mslp": 101460,
            "screenRelativeHumidity": 74.19,
            "feelsLikeTemp": 23.06,
            "uvIndex": 0,
            "probOfPrecipitation": 68,
            "probOfSnow": 0,
            "probOfHeavySnow": 0,
            "probOfRain": 68,
            "probOfHeavyRain": 65,
            "probOfHail": 14,
            "probOfSferics": 19
          },
          {
            "time": "2022-06-05T00:00Z",
            "maxScreenAirTemp": 22.31,
            "minScreenAirTemp": 19.24,
            "max10mWindGust": 7.53,
            "significantWeatherCode": 13,
            "totalPrecipAmount": 3.91,
            "totalSnowAmount": 0,
            "windSpeed10m": 2.32,
            "windDirectionFrom10m": 320,
            "windGustSpeed10m": 5.56,
            "visibility": 14588,
            "mslp": 101380,
            "screenRelativeHumidity": 89.71,
            "feelsLikeTemp": 19.8,
            "uvIndex": 0,
            "probOfPrecipitation": 64,
            "probOfSnow": 0,
            "probOfHeavySnow": 0,
            "probOfRain": 64,
            "probOfHeavyRain": 62,
            "probOfHail": 13,
            "probOfSferics": 17
          },
          {
            "time": "2022-06-05T03:00Z",
            "maxScreenAirTemp": 19.25,
            "minScreenAirTemp": 18.1,
            "max10mWindGust": 5.32,
            "significantWeatherCode": 12,
            "totalPrecipAmount": 0.75,
            "totalSnowAmount": 0,
            "windSpeed10m": 1.81,
            "windDirectionFrom10m": 265,
            "windGustSpeed10m": 4.02,
            "visibility": 17143,
            "mslp": 101250,
            "screenRelativeHumidity": 93.3,
            "feelsLikeTemp": 18.81,
            "uvIndex": 0,
            "probOfPrecipitation": 43,
            "probOfSnow": 0,
            "probOfHeavySnow": 0,
            "probOfRain": 43,
            "probOfHeavyRain": 24,
            "probOfHail": 2,
            "probOfSferics": 2
          },
          {
            "time": "2022-06-05T06:00Z",
            "maxScreenAirTemp": 18.11,
            "minScreenAirTemp": 17.81,
            "max10mWindGust": 6.85,
            "significantWeatherCode": 7,
            "totalPrecipAmount": 0,
            "totalSnowAmount": 0,
            "windSpeed10m": 3,
            "windDirectionFrom10m": 253,
            "windGustSpeed10m": 6.65,
            "visibility": 18830,
            "mslp": 101360,
            "screenRelativeHumidity": 90.66,
            "feelsLikeTemp": 17.75,
            "uvIndex": 1,
            "probOfPrecipitation": 10,
            "probOfSnow": 0,
            "probOfHeavySnow": 0,
            "probOfRain": 10,
            "probOfHeavyRain": 5,
            "probOfHail": 1,
            "probOfSferics": 1
          },
          {
            "time": "2022-06-05T09:00Z",
            "maxScreenAirTemp": 20.01,
            "minScreenAirTemp": 17.89,
            "max10mWindGust": 10.42,
            "significantWeatherCode": 10,
            "totalPrecipAmount": 0.13,
            "totalSnowAmount": 0,
            "windSpeed10m": 4.34,
            "windDirectionFrom10m": 256,
            "windGustSpeed10m": 10.15,
            "visibility": 17266,
            "mslp": 101500,
            "screenRelativeHumidity": 74.93,
            "feelsLikeTemp": 18.83,
            "uvIndex": 4,
            "probOfPrecipitation": 32,
            "probOfSnow": 0,
            "probOfHeavySnow": 0,
            "probOfRain": 32,
            "probOfHeavyRain": 16,
            "probOfHail": 0,
            "probOfSferics": 4
          },
          {
            "time": "2022-06-05T12:00Z",
            "maxScreenAirTemp": 22.72,
            "minScreenAirTemp": 20,
            "max10mWindGust": 12.12,
            "significantWeatherCode": 1,
            "totalPrecipAmount": 0,
            "totalSnowAmount": 0,
            "windSpeed10m": 5.04,
            "windDirectionFrom10m": 255,
            "windGustSpeed10m": 12.03,
            "visibility": 26751,
            "mslp": 101570,
            "screenRelativeHumidity": 56.18,
            "feelsLikeTemp": 20.75,
            "uvIndex": 7,
            "probOfPrecipitation": 8,
            "probOfSnow": 0,
            "probOfHeavySnow": 0,
            "probOfRain": 8,
            "probOfHeavyRain": 5,
            "probOfHail": 0,
            "probOfSferics": 2
          },
          {
            "time": "2022-06-05T15:00Z",
            "maxScreenAirTemp": 23.67,
            "minScreenAirTemp": 22.71,
            "max10mWindGust": 12.93,
            "significantWeatherCode": 3,
            "totalPrecipAmount": 0,
            "totalSnowAmount": 0,
            "windSpeed10m": 5.16,
            "windDirectionFrom10m": 259,
            "windGustSpeed10m": 12.23,
            "visibility": 24109,
            "mslp": 101610,
            "screenRelativeHumidity": 48.12,
            "feelsLikeTemp": 21.22,
            "uvIndex": 3,
            "probOfPrecipitation": 9,
            "probOfSnow": 0,
            "probOfHeavySnow": 0,
            "probOfRain": 9,
            "probOfHeavyRain": 6,
            "probOfHail": 1,
            "probOfSferics": 2
          },
          {
            "time": "2022-06-05T18:00Z",
            "maxScreenAirTemp": 23.56,
            "minScreenAirTemp": 21.4,
            "max10mWindGust": 12.33,
            "significantWeatherCode": 3,
            "totalPrecipAmount": 0,
            "totalSnowAmount": 0,
            "windSpeed10m": 4.19,
            "windDirectionFrom10m": 260,
            "windGustSpeed10m": 9.97,
            "visibility": 19658,
            "mslp": 101660,
            "screenRelativeHumidity": 55.77,
            "feelsLikeTemp": 19.68,
            "uvIndex": 1,
            "probOfPrecipitation": 12,
            "probOfSnow": 0,
            "probOfHeavySnow": 0,
            "probOfRain": 12,
            "probOfHeavyRain": 8,
            "probOfHail": 1,
            "probOfSferics": 3
          },
          {
            "time": "2022-06-05T21:00Z",
            "maxScreenAirTemp": 21.42,
            "minScreenAirTemp": 18.81,
            "max10mWindGust": 9.06,
            "significantWeatherCode": 9,
            "totalPrecipAmount": 0.29,
            "totalSnowAmount": 0,
            "windSpeed10m": 3.16,
            "windDirectionFrom10m": 253,
            "windGustSpeed10m": 7.14,
            "visibility": 25394,
            "mslp": 101790,
            "screenRelativeHumidity": 66.46,
            "feelsLikeTemp": 17.77,
            "uvIndex": 0,
            "probOfPrecipitation": 38,
            "probOfSnow": 0,
            "probOfHeavySnow": 0,
            "probOfRain": 38,
            "probOfHeavyRain": 20,
            "probOfHail": 1,
            "probOfSferics": 5
          },
          {
            "time": "2022-06-06T00:00Z",
            "maxScreenAirTemp": 18.81,
            "minScreenAirTemp": 16.86,
            "max10mWindGust": 7.3,
            "significantWeatherCode": 7,
            "totalPrecipAmount": 0,
            "totalSnowAmount": 0,
            "windSpeed10m": 2.72,
            "windDirectionFrom10m": 244,
            "windGustSpeed10m": 5.99,
            "visibility": 25496,
            "mslp": 101790,
            "screenRelativeHumidity": 73.11,
            "feelsLikeTemp": 16.15,
            "uvIndex": 0,
            "probOfPrecipitation": 9,
            "probOfSnow": 0,
            "probOfHeavySnow": 0,
            "probOfRain": 9,
            "probOfHeavyRain": 3,
            "probOfHail": 0,
            "probOfSferics": 1
          },
          {
            "time": "2022-06-06T03:00Z",
            "maxScreenAirTemp": 16.87,
            "minScreenAirTemp": 14.98,
            "max10mWindGust": 7.57,
            "significantWeatherCode": 0,
            "totalPrecipAmount": 0,
            "totalSnowAmount": 0,
            "windSpeed10m": 3.18,
            "windDirectionFrom10m": 238,
            "windGustSpeed10m": 6.96,
            "visibility": 25022,
            "mslp": 101740,
            "screenRelativeHumidity": 79.24,
            "feelsLikeTemp": 13.96,
            "uvIndex": 0,
            "probOfPrecipitation": 2,
            "probOfSnow": 0,
            "probOfHeavySnow": 0,
            "probOfRain": 2,
            "probOfHeavyRain": 1,
            "probOfHail": 0,
            "probOfSferics": 0
          },
          {
            "time": "2022-06-06T06:00Z",
            "maxScreenAirTemp": 14.98,
            "minScreenAirTemp": 14.3,
            "max10mWindGust": 7.28,
            "significantWeatherCode": 3,
            "totalPrecipAmount": 0,
            "totalSnowAmount": 0,
            "windSpeed10m": 3.14,
            "windDirectionFrom10m": 238,
            "windGustSpeed10m": 7.1,
            "visibility": 24470,
            "mslp": 101820,
            "screenRelativeHumidity": 79.38,
            "feelsLikeTemp": 13.45,
            "uvIndex": 1,
            "probOfPrecipitation": 1,
            "probOfSnow": 0,
            "probOfHeavySnow": 0,
            "probOfRain": 1,
            "probOfHeavyRain": 1,
            "probOfHail": 0,
            "probOfSferics": 0
          },
          {
            "time": "2022-06-06T09:00Z",
            "maxScreenAirTemp": 17.62,
            "minScreenAirTemp": 14.5,
            "max10mWindGust": 8.82,
            "significantWeatherCode": 3,
            "totalPrecipAmount": 0,
            "totalSnowAmount": 0,
            "windSpeed10m": 3.64,
            "windDirectionFrom10m": 238,
            "windGustSpeed10m": 8.82,
            "visibility": 26998,
            "mslp": 101850,
            "screenRelativeHumidity": 57.8,
            "feelsLikeTemp": 16.02,
            "uvIndex": 5,
            "probOfPrecipitation": 2,
            "probOfSnow": 0,
            "probOfHeavySnow": 0,
            "probOfRain": 2,
            "probOfHeavyRain": 1,
            "probOfHail": 0,
            "probOfSferics": 0
          },
          {
            "time": "2022-06-06T12:00Z",
            "maxScreenAirTemp": 20.73,
            "minScreenAirTemp": 17.62,
            "max10mWindGust": 10.35,
            "significantWeatherCode": 7,
            "totalPrecipAmount": 0,
            "totalSnowAmount": 0,
            "windSpeed10m": 3.96,
            "windDirectionFrom10m": 236,
            "windGustSpeed10m": 10.16,
            "visibility": 24835,
            "mslp": 101770,
            "screenRelativeHumidity": 43.03,
            "feelsLikeTemp": 18.39,
            "uvIndex": 6,
            "probOfPrecipitation": 4,
            "probOfSnow": 0,
            "probOfHeavySnow": 0,
            "probOfRain": 4,
            "probOfHeavyRain": 0,
            "probOfHail": 0,
            "probOfSferics": 0
          },
          {
            "time": "2022-06-06T15:00Z",
            "maxScreenAirTemp": 21.85,
            "minScreenAirTemp": 20.72,
            "max10mWindGust": 10.67,
            "significantWeatherCode": 7,
            "totalPrecipAmount": 0,
            "totalSnowAmount": 0,
            "windSpeed10m": 4.12,
            "windDirectionFrom10m": 237,
            "windGustSpeed10m": 10.16,
            "visibility": 26292,
            "mslp": 101690,
            "screenRelativeHumidity": 42.01,
            "feelsLikeTemp": 19.35,
            "uvIndex": 3,
            "probOfPrecipitation": 6,
            "probOfSnow": 0,
            "probOfHeavySnow": 0,
            "probOfRain": 6,
            "probOfHeavyRain": 1,
            "probOfHail": 0,
            "probOfSferics": 0
          },
          {
            "time": "2022-06-06T18:00Z",
            "maxScreenAirTemp": 21.69,
            "minScreenAirTemp": 20.19,
            "max10mWindGust": 11.22,
            "significantWeatherCode": 7,
            "totalPrecipAmount": 0,
            "totalSnowAmount": 0,
            "windSpeed10m": 3.99,
            "windDirectionFrom10m": 230,
            "windGustSpeed10m": 9.36,
            "visibility": 26074,
            "mslp": 101620,
            "screenRelativeHumidity": 54.28,
            "feelsLikeTemp": 18.31,
            "uvIndex": 1,
            "probOfPrecipitation": 15,
            "probOfSnow": 0,
            "probOfHeavySnow": 0,
            "probOfRain": 15,
            "probOfHeavyRain": 7,
            "probOfHail": 0,
            "probOfSferics": 1
          },
          {
            "time": "2022-06-06T21:00Z",
            "maxScreenAirTemp": 20.21,
            "minScreenAirTemp": 18.21,
            "max10mWindGust": 9.89,
            "significantWeatherCode": 9,
            "totalPrecipAmount": 0.18,
            "totalSnowAmount": 0,
            "windSpeed10m": 3.04,
            "windDirectionFrom10m": 219,
            "windGustSpeed10m": 6.89,
            "visibility": 25478,
            "mslp": 101640,
            "screenRelativeHumidity": 65.92,
            "feelsLikeTemp": 17.22,
            "uvIndex": 0,
            "probOfPrecipitation": 34,
            "probOfSnow": 0,
            "probOfHeavySnow": 0,
            "probOfRain": 34,
            "probOfHeavyRain": 18,
            "probOfHail": 0,
            "probOfSferics": 4
          },
          {
            "time": "2022-06-07T00:00Z",
            "maxScreenAirTemp": 18.22,
            "minScreenAirTemp": 16.87,
            "max10mWindGust": 7.69,
            "significantWeatherCode": 2,
            "totalPrecipAmount": 0,
            "totalSnowAmount": 0,
            "windSpeed10m": 3.03,
            "windDirectionFrom10m": 212,
            "windGustSpeed10m": 6.72,
            "visibility": 22632,
            "mslp": 101560,
            "screenRelativeHumidity": 77.22,
            "feelsLikeTemp": 16.1,
            "uvIndex": 0,
            "probOfPrecipitation": 8,
            "probOfSnow": 0,
            "probOfHeavySnow": 0,
            "probOfRain": 8,
            "probOfHeavyRain": 5,
            "probOfHail": 1,
            "probOfSferics": 1
          },
          {
            "time": "2022-06-07T03:00Z",
            "maxScreenAirTemp": 16.88,
            "minScreenAirTemp": 15.85,
            "max10mWindGust": 7.66,
            "significantWeatherCode": 2,
            "totalPrecipAmount": 0,
            "totalSnowAmount": 0,
            "windSpeed10m": 3.09,
            "windDirectionFrom10m": 211,
            "windGustSpeed10m": 6.75,
            "visibility": 18535,
            "mslp": 101450,
            "screenRelativeHumidity": 84.69,
            "feelsLikeTemp": 15.11,
            "uvIndex": 0,
            "probOfPrecipitation": 10,
            "probOfSnow": 0,
            "probOfHeavySnow": 0,
            "probOfRain": 10,
            "probOfHeavyRain": 7,
            "probOfHail": 1,
            "probOfSferics": 1
          },
          {
            "time": "2022-06-07T06:00Z",
            "maxScreenAirTemp": 15.86,
            "minScreenAirTemp": 15.54,
            "max10mWindGust": 8.16,
            "significantWeatherCode": 7,
            "totalPrecipAmount": 0,
            "totalSnowAmount": 0,
            "windSpeed10m": 3.58,
            "windDirectionFrom10m": 218,
            "windGustSpeed10m": 7.97,
            "visibility": 12785,
            "mslp": 101490,
            "screenRelativeHumidity": 84.15,
            "feelsLikeTemp": 14.59,
            "uvIndex": 1,
            "probOfPrecipitation": 14,
            "probOfSnow": 0,
            "probOfHeavySnow": 0,
            "probOfRain": 14,
            "probOfHeavyRain": 7,
            "probOfHail": 1,
            "probOfSferics": 1
          },
          {
            "time": "2022-06-07T09:00Z",
            "maxScreenAirTemp": 17.65,
            "minScreenAirTemp": 15.62,
            "max10mWindGust": 10.11,
            "significantWeatherCode": 10,
            "totalPrecipAmount": 0.41,
            "totalSnowAmount": 0,
            "windSpeed10m": 4.21,
            "windDirectionFrom10m": 235,
            "windGustSpeed10m": 9.79,
            "visibility": 19041,
            "mslp": 101500,
            "screenRelativeHumidity": 75.64,
            "feelsLikeTemp": 16.26,
            "uvIndex": 5,
            "probOfPrecipitation": 38,
            "probOfSnow": 0,
            "probOfHeavySnow": 0,
            "probOfRain": 38,
            "probOfHeavyRain": 19,
            "probOfHail": 0,
            "probOfSferics": 4
          },
          {
            "time": "2022-06-07T12:00Z",
            "maxScreenAirTemp": 20.71,
            "minScreenAirTemp": 17.63,
            "max10mWindGust": 11.09,
            "significantWeatherCode": 10,
            "totalPrecipAmount": 0.47,
            "totalSnowAmount": 0,
            "windSpeed10m": 4.41,
            "windDirectionFrom10m": 263,
            "windGustSpeed10m": 10.72,
            "visibility": 22298,
            "mslp": 101480,
            "screenRelativeHumidity": 56.91,
            "feelsLikeTemp": 18.7,
            "uvIndex": 5,
            "probOfPrecipitation": 40,
            "probOfSnow": 0,
            "probOfHeavySnow": 0,
            "probOfRain": 40,
            "probOfHeavyRain": 23,
            "probOfHail": 1,
            "probOfSferics": 6
          },
          {
            "time": "2022-06-07T15:00Z",
            "maxScreenAirTemp": 22.35,
            "minScreenAirTemp": 20.66,
            "max10mWindGust": 12.02,
            "significantWeatherCode": 10,
            "totalPrecipAmount": 0.29,
            "totalSnowAmount": 0,
            "windSpeed10m": 4.56,
            "windDirectionFrom10m": 272,
            "windGustSpeed10m": 11.11,
            "visibility": 24138,
            "mslp": 101470,
            "screenRelativeHumidity": 46.26,
            "feelsLikeTemp": 20.01,
            "uvIndex": 3,
            "probOfPrecipitation": 37,
            "probOfSnow": 0,
            "probOfHeavySnow": 0,
            "probOfRain": 37,
            "probOfHeavyRain": 20,
            "probOfHail": 1,
            "probOfSferics": 5
          },
          {
            "time": "2022-06-07T18:00Z",
            "maxScreenAirTemp": 22.3,
            "minScreenAirTemp": 21.08,
            "max10mWindGust": 11.86,
            "significantWeatherCode": 3,
            "totalPrecipAmount": 0,
            "totalSnowAmount": 0,
            "windSpeed10m": 4.04,
            "windDirectionFrom10m": 280,
            "windGustSpeed10m": 9.59,
            "visibility": 24936,
            "mslp": 101500,
            "screenRelativeHumidity": 52.71,
            "feelsLikeTemp": 19.29,
            "uvIndex": 1,
            "probOfPrecipitation": 15,
            "probOfSnow": 0,
            "probOfHeavySnow": 0,
            "probOfRain": 15,
            "probOfHeavyRain": 9,
            "probOfHail": 1,
            "probOfSferics": 2
          },
          {
            "time": "2022-06-07T21:00Z",
            "maxScreenAirTemp": 21.14,
            "minScreenAirTemp": 18.89,
            "max10mWindGust": 10.07,
            "significantWeatherCode": 9,
            "totalPrecipAmount": 0.11,
            "totalSnowAmount": 0,
            "windSpeed10m": 2.42,
            "windDirectionFrom10m": 279,
            "windGustSpeed10m": 5.58,
            "visibility": 26770,
            "mslp": 101590,
            "screenRelativeHumidity": 63.11,
            "feelsLikeTemp": 18.23,
            "uvIndex": 0,
            "probOfPrecipitation": 33,
            "probOfSnow": 0,
            "probOfHeavySnow": 0,
            "probOfRain": 33,
            "probOfHeavyRain": 17,
            "probOfHail": 0,
            "probOfSferics": 4
          },
          {
            "time": "2022-06-08T00:00Z",
            "maxScreenAirTemp": 18.89,
            "minScreenAirTemp": 17.28,
            "max10mWindGust": 6.54,
            "significantWeatherCode": 7,
            "totalPrecipAmount": 0,
            "totalSnowAmount": 0,
            "windSpeed10m": 2.09,
            "windDirectionFrom10m": 248,
            "windGustSpeed10m": 4.58,
            "visibility": 26368,
            "mslp": 101530,
            "screenRelativeHumidity": 70.45,
            "feelsLikeTemp": 17,
            "uvIndex": 0,
            "probOfPrecipitation": 5,
            "probOfSnow": 0,
            "probOfHeavySnow": 0,
            "probOfRain": 5,
            "probOfHeavyRain": 1,
            "probOfHail": 0,
            "probOfSferics": 0
          },
          {
            "time": "2022-06-08T03:00Z",
            "maxScreenAirTemp": 17.39,
            "minScreenAirTemp": 15.75,
            "max10mWindGust": 6.02,
            "significantWeatherCode": 7,
            "totalPrecipAmount": 0,
            "totalSnowAmount": 0,
            "windSpeed10m": 2.33,
            "windDirectionFrom10m": 226,
            "windGustSpeed10m": 4.98,
            "visibility": 21477,
            "mslp": 101440,
            "screenRelativeHumidity": 77.6,
            "feelsLikeTemp": 15.24,
            "uvIndex": 0,
            "probOfPrecipitation": 6,
            "probOfSnow": 0,
            "probOfHeavySnow": 0,
            "probOfRain": 6,
            "probOfHeavyRain": 1,
            "probOfHail": 0,
            "probOfSferics": 0
          },
          {
            "time": "2022-06-08T06:00Z",
            "maxScreenAirTemp": 15.75,
            "minScreenAirTemp": 15.44,
            "max10mWindGust": 6.78,
            "significantWeatherCode": 12,
            "totalPrecipAmount": 0.49,
            "totalSnowAmount": 0,
            "windSpeed10m": 2.91,
            "windDirectionFrom10m": 213,
            "windGustSpeed10m": 6.58,
            "visibility": 20849,
            "mslp": 101460,
            "screenRelativeHumidity": 82.49,
            "feelsLikeTemp": 14.87,
            "uvIndex": 1,
            "probOfPrecipitation": 53,
            "probOfSnow": 0,
            "probOfHeavySnow": 0,
            "probOfRain": 53,
            "probOfHeavyRain": 36,
            "probOfHail": 4,
            "probOfSferics": 2
          },
          {
            "time": "2022-06-08T09:00Z",
            "maxScreenAirTemp": 17.6,
            "minScreenAirTemp": 15.59,
            "max10mWindGust": 9.24,
            "significantWeatherCode": 7,
            "totalPrecipAmount": 0,
            "totalSnowAmount": 0,
            "windSpeed10m": 3.93,
            "windDirectionFrom10m": 213,
            "windGustSpeed10m": 9.06,
            "visibility": 17809,
            "mslp": 101440,
            "screenRelativeHumidity": 74.91,
            "feelsLikeTemp": 16.31,
            "uvIndex": 4,
            "probOfPrecipitation": 16,
            "probOfSnow": 0,
            "probOfHeavySnow": 0,
            "probOfRain": 16,
            "probOfHeavyRain": 8,
            "probOfHail": 1,
            "probOfSferics": 1
          },
          {
            "time": "2022-06-08T12:00Z",
            "maxScreenAirTemp": 19.3,
            "minScreenAirTemp": 17.59,
            "max10mWindGust": 10.53,
            "significantWeatherCode": 12,
            "totalPrecipAmount": 0.86,
            "totalSnowAmount": 0,
            "windSpeed10m": 4.3,
            "windDirectionFrom10m": 223,
            "windGustSpeed10m": 9.92,
            "visibility": 14084,
            "mslp": 101390,
            "screenRelativeHumidity": 69.07,
            "feelsLikeTemp": 17.64,
            "uvIndex": 4,
            "probOfPrecipitation": 51,
            "probOfSnow": 0,
            "probOfHeavySnow": 0,
            "probOfRain": 51,
            "probOfHeavyRain": 33,
            "probOfHail": 3,
            "probOfSferics": 4
          },
          {
            "time": "2022-06-08T15:00Z",
            "maxScreenAirTemp": 20.26,
            "minScreenAirTemp": 19.2,
            "max10mWindGust": 11.09,
            "significantWeatherCode": 12,
            "totalPrecipAmount": 1.25,
            "totalSnowAmount": 0,
            "windSpeed10m": 4.33,
            "windDirectionFrom10m": 237,
            "windGustSpeed10m": 9.92,
            "visibility": 21233,
            "mslp": 101350,
            "screenRelativeHumidity": 66.42,
            "feelsLikeTemp": 18.57,
            "uvIndex": 2,
            "probOfPrecipitation": 55,
            "probOfSnow": 0,
            "probOfHeavySnow": 0,
            "probOfRain": 55,
            "probOfHeavyRain": 37,
            "probOfHail": 4,
            "probOfSferics": 4
          },
          {
            "time": "2022-06-08T18:00Z",
            "maxScreenAirTemp": 20.21,
            "minScreenAirTemp": 19.79,
            "max10mWindGust": 11.21,
            "significantWeatherCode": 3,
            "totalPrecipAmount": 0,
            "totalSnowAmount": 0,
            "windSpeed10m": 4.1,
            "windDirectionFrom10m": 241,
            "windGustSpeed10m": 9.31,
            "visibility": 21929,
            "mslp": 101360,
            "screenRelativeHumidity": 65.83,
            "feelsLikeTemp": 18.41,
            "uvIndex": 1,
            "probOfPrecipitation": 13,
            "probOfSnow": 0,
            "probOfHeavySnow": 0,
            "probOfRain": 13,
            "probOfHeavyRain": 9,
            "probOfHail": 1,
            "probOfSferics": 1
          },
          {
            "time": "2022-06-08T21:00Z",
            "maxScreenAirTemp": 19.88,
            "minScreenAirTemp": 18.22,
            "max10mWindGust": 9.8,
            "significantWeatherCode": 2,
            "totalPrecipAmount": 0,
            "totalSnowAmount": 0,
            "windSpeed10m": 3.27,
            "windDirectionFrom10m": 246,
            "windGustSpeed10m": 7.25,
            "visibility": 20898,
            "mslp": 101450,
            "screenRelativeHumidity": 74.36,
            "feelsLikeTemp": 17.38,
            "uvIndex": 0,
            "probOfPrecipitation": 10,
            "probOfSnow": 0,
            "probOfHeavySnow": 0,
            "probOfRain": 10,
            "probOfHeavyRain": 7,
            "probOfHail": 1,
            "probOfSferics": 1
          },
          {
            "time": "2022-06-09T00:00Z",
            "maxScreenAirTemp": 18.22,
            "minScreenAirTemp": 16.81,
            "max10mWindGust": 8.29,
            "significantWeatherCode": 7,
            "totalPrecipAmount": 0,
            "totalSnowAmount": 0,
            "windSpeed10m": 3.02,
            "windDirectionFrom10m": 256,
            "windGustSpeed10m": 6.52,
            "visibility": 22156,
            "mslp": 101480,
            "screenRelativeHumidity": 79.63,
            "feelsLikeTemp": 16.13,
            "uvIndex": 0,
            "probOfPrecipitation": 9,
            "probOfSnow": 0,
            "probOfHeavySnow": 0,
            "probOfRain": 9,
            "probOfHeavyRain": 3,
            "probOfHail": 0,
            "probOfSferics": 1
          },
          {
            "time": "2022-06-09T03:00Z",
            "maxScreenAirTemp": 16.82,
            "minScreenAirTemp": 15.43,
            "max10mWindGust": 7.43,
            "significantWeatherCode": 7,
            "totalPrecipAmount": 0,
            "totalSnowAmount": 0,
            "windSpeed10m": 2.85,
            "windDirectionFrom10m": 247,
            "windGustSpeed10m": 6.1,
            "visibility": 20755,
            "mslp": 101500,
            "screenRelativeHumidity": 83.76,
            "feelsLikeTemp": 14.77,
            "uvIndex": 0,
            "probOfPrecipitation": 8,
            "probOfSnow": 0,
            "probOfHeavySnow": 0,
            "probOfRain": 8,
            "probOfHeavyRain": 4,
            "probOfHail": 0,
            "probOfSferics": 0
          },
          {
            "time": "2022-06-09T06:00Z",
            "maxScreenAirTemp": 15.67,
            "minScreenAirTemp": 15.23,
            "max10mWindGust": 6.95,
            "significantWeatherCode": 7,
            "totalPrecipAmount": 0,
            "totalSnowAmount": 0,
            "windSpeed10m": 3,
            "windDirectionFrom10m": 243,
            "windGustSpeed10m": 6.63,
            "visibility": 19438,
            "mslp": 101630,
            "screenRelativeHumidity": 82.9,
            "feelsLikeTemp": 14.71,
            "uvIndex": 1,
            "probOfPrecipitation": 9,
            "probOfSnow": 0,
            "probOfHeavySnow": 0,
            "probOfRain": 9,
            "probOfHeavyRain": 4,
            "probOfHail": 1,
            "probOfSferics": 1
          },
          {
            "time": "2022-06-09T09:00Z",
            "maxScreenAirTemp": 17.83,
            "minScreenAirTemp": 15.46,
            "max10mWindGust": 8.31,
            "significantWeatherCode": 7,
            "totalPrecipAmount": 0,
            "totalSnowAmount": 0,
            "windSpeed10m": 3.52,
            "windDirectionFrom10m": 240,
            "windGustSpeed10m": 8.2,
            "visibility": 23331,
            "mslp": 101690,
            "screenRelativeHumidity": 69.11,
            "feelsLikeTemp": 16.67,
            "uvIndex": 4,
            "probOfPrecipitation": 10,
            "probOfSnow": 0,
            "probOfHeavySnow": 0,
            "probOfRain": 10,
            "probOfHeavyRain": 4,
            "probOfHail": 1,
            "probOfSferics": 1
          },
          {
            "time": "2022-06-09T12:00Z",
            "maxScreenAirTemp": 21,
            "minScreenAirTemp": 17.82,
            "max10mWindGust": 10.7,
            "significantWeatherCode": 7,
            "totalPrecipAmount": 0,
            "totalSnowAmount": 0,
            "windSpeed10m": 4.38,
            "windDirectionFrom10m": 241,
            "windGustSpeed10m": 10.49,
            "visibility": 25100,
            "mslp": 101700,
            "screenRelativeHumidity": 55.56,
            "feelsLikeTemp": 19.07,
            "uvIndex": 5,
            "probOfPrecipitation": 9,
            "probOfSnow": 0,
            "probOfHeavySnow": 0,
            "probOfRain": 9,
            "probOfHeavyRain": 2,
            "probOfHail": 0,
            "probOfSferics": 0
          },
          {
            "time": "2022-06-09T15:00Z",
            "maxScreenAirTemp": 22.37,
            "minScreenAirTemp": 20.98,
            "max10mWindGust": 11.11,
            "significantWeatherCode": 7,
            "totalPrecipAmount": 0,
            "totalSnowAmount": 0,
            "windSpeed10m": 4.52,
            "windDirectionFrom10m": 245,
            "windGustSpeed10m": 10.55,
            "visibility": 24631,
            "mslp": 101680,
            "screenRelativeHumidity": 52.84,
            "feelsLikeTemp": 20.42,
            "uvIndex": 3,
            "probOfPrecipitation": 13,
            "probOfSnow": 0,
            "probOfHeavySnow": 0,
            "probOfRain": 13,
            "probOfHeavyRain": 6,
            "probOfHail": 0,
            "probOfSferics": 1
          },
          {
            "time": "2022-06-09T18:00Z",
            "maxScreenAirTemp": 22.52,
            "minScreenAirTemp": 22.15,
            "max10mWindGust": 11.22,
            "significantWeatherCode": 7,
            "totalPrecipAmount": 0,
            "totalSnowAmount": 0,
            "windSpeed10m": 4.19,
            "windDirectionFrom10m": 243,
            "windGustSpeed10m": 9.57,
            "visibility": 25117,
            "mslp": 101661,
            "screenRelativeHumidity": 54.02,
            "feelsLikeTemp": 20.7,
            "uvIndex": 1,
            "probOfPrecipitation": 7,
            "probOfSnow": 0,
            "probOfHeavySnow": 0,
            "probOfRain": 7,
            "probOfHeavyRain": 2,
            "probOfHail": 0,
            "probOfSferics": 1
          },
          {
            "time": "2022-06-09T21:00Z",
            "maxScreenAirTemp": 22.3,
            "minScreenAirTemp": 20.55,
            "max10mWindGust": 10,
            "significantWeatherCode": 0,
            "totalPrecipAmount": 0,
            "totalSnowAmount": 0,
            "windSpeed10m": 3.7,
            "windDirectionFrom10m": 240,
            "windGustSpeed10m": 8.05,
            "visibility": 26010,
            "mslp": 101739,
            "screenRelativeHumidity": 62.43,
            "feelsLikeTemp": 19.37,
            "uvIndex": 0,
            "probOfPrecipitation": 3,
            "probOfSnow": 0,
            "probOfHeavySnow": 0,
            "probOfRain": 3,
            "probOfHeavyRain": 1,
            "probOfHail": 0,
            "probOfSferics": 0
          },
          {
            "time": "2022-06-10T00:00Z",
            "maxScreenAirTemp": 20.55,
            "minScreenAirTemp": 18.71,
            "max10mWindGust": 8.69,
            "significantWeatherCode": 0,
            "totalPrecipAmount": 0,
            "totalSnowAmount": 0,
            "windSpeed10m": 3.52,
            "windDirectionFrom10m": 241,
            "windGustSpeed10m": 7.4,
            "visibility": 24474,
            "mslp": 101777,
            "screenRelativeHumidity": 71.56,
            "feelsLikeTemp": 17.78,
            "uvIndex": 0,
            "probOfPrecipitation": 3,
            "probOfSnow": 0,
            "probOfHeavySnow": 0,
            "probOfRain": 3,
            "probOfHeavyRain": 2,
            "probOfHail": 0,
            "probOfSferics": 0
          },
          {
            "time": "2022-06-10T03:00Z",
            "maxScreenAirTemp": 18.72,
            "minScreenAirTemp": 17.35,
            "max10mWindGust": 7.08,
            "significantWeatherCode": 0,
            "totalPrecipAmount": 0,
            "totalSnowAmount": 0,
            "windSpeed10m": 3.15,
            "windDirectionFrom10m": 224,
            "windGustSpeed10m": 6.51,
            "visibility": 22221,
            "mslp": 101792,
            "screenRelativeHumidity": 78.07,
            "feelsLikeTemp": 16.67,
            "uvIndex": 0,
            "probOfPrecipitation": 4,
            "probOfSnow": 0,
            "probOfHeavySnow": 0,
            "probOfRain": 4,
            "probOfHeavyRain": 3,
            "probOfHail": 0,
            "probOfSferics": 0
          },
          {
            "time": "2022-06-10T06:00Z",
            "maxScreenAirTemp": 17.36,
            "minScreenAirTemp": 16.81,
            "max10mWindGust": 6.82,
            "significantWeatherCode": 3,
            "totalPrecipAmount": 0,
            "totalSnowAmount": 0,
            "windSpeed10m": 3.15,
            "windDirectionFrom10m": 230,
            "windGustSpeed10m": 6.82,
            "visibility": 22637,
            "mslp": 101878,
            "screenRelativeHumidity": 79.8,
            "feelsLikeTemp": 16.29,
            "uvIndex": 2,
            "probOfPrecipitation": 5,
            "probOfSnow": 0,
            "probOfHeavySnow": 0,
            "probOfRain": 5,
            "probOfHeavyRain": 2,
            "probOfHail": 0,
            "probOfSferics": 0
          },
          {
            "time": "2022-06-10T09:00Z",
            "maxScreenAirTemp": 19.03,
            "minScreenAirTemp": 16.98,
            "max10mWindGust": 7.96,
            "significantWeatherCode": 1,
            "totalPrecipAmount": 0,
            "totalSnowAmount": 0,
            "windSpeed10m": 3.44,
            "windDirectionFrom10m": 237,
            "windGustSpeed10m": 7.96,
            "visibility": 26279,
            "mslp": 101924,
            "screenRelativeHumidity": 67.06,
            "feelsLikeTemp": 17.95,
            "uvIndex": 5,
            "probOfPrecipitation": 3,
            "probOfSnow": 0,
            "probOfHeavySnow": 0,
            "probOfRain": 3,
            "probOfHeavyRain": 2,
            "probOfHail": 0,
            "probOfSferics": 0
          },
          {
            "time": "2022-06-10T12:00Z",
            "maxScreenAirTemp": 22.28,
            "minScreenAirTemp": 19.02,
            "max10mWindGust": 9.29,
            "significantWeatherCode": 1,
            "totalPrecipAmount": 0,
            "totalSnowAmount": 0,
            "windSpeed10m": 3.8,
            "windDirectionFrom10m": 230,
            "windGustSpeed10m": 9.29,
            "visibility": 28021,
            "mslp": 101918,
            "screenRelativeHumidity": 53.15,
            "feelsLikeTemp": 20.85,
            "uvIndex": 7,
            "probOfPrecipitation": 4,
            "probOfSnow": 0,
            "probOfHeavySnow": 0,
            "probOfRain": 4,
            "probOfHeavyRain": 2,
            "probOfHail": 0,
            "probOfSferics": 0
          },
          {
            "time": "2022-06-10T15:00Z",
            "maxScreenAirTemp": 24.3,
            "minScreenAirTemp": 22.28,
            "max10mWindGust": 9.71,
            "significantWeatherCode": 1,
            "totalPrecipAmount": 0,
            "totalSnowAmount": 0,
            "windSpeed10m": 3.97,
            "windDirectionFrom10m": 232,
            "windGustSpeed10m": 9.66,
            "visibility": 28421,
            "mslp": 101849,
            "screenRelativeHumidity": 46.93,
            "feelsLikeTemp": 22.8,
            "uvIndex": 3,
            "probOfPrecipitation": 4,
            "probOfSnow": 0,
            "probOfHeavySnow": 0,
            "probOfRain": 4,
            "probOfHeavyRain": 2,
            "probOfHail": 0,
            "probOfSferics": 0
          },
          {
            "time": "2022-06-10T18:00Z",
            "maxScreenAirTemp": 24.42,
            "minScreenAirTemp": 24.24,
            "max10mWindGust": 10.13,
            "significantWeatherCode": 1,
            "totalPrecipAmount": 0,
            "totalSnowAmount": 0,
            "windSpeed10m": 3.95,
            "windDirectionFrom10m": 241,
            "windGustSpeed10m": 9.18,
            "visibility": 28550,
            "mslp": 101785,
            "screenRelativeHumidity": 47.16,
            "feelsLikeTemp": 22.82,
            "uvIndex": 1,
            "probOfPrecipitation": 3,
            "probOfSnow": 0,
            "probOfHeavySnow": 0,
            "probOfRain": 3,
            "probOfHeavyRain": 2,
            "probOfHail": 0,
            "probOfSferics": 0
          },
          {
            "time": "2022-06-10T21:00Z",
            "maxScreenAirTemp": 24.24,
            "minScreenAirTemp": 21.94,
            "max10mWindGust": 9.58,
            "significantWeatherCode": 0,
            "totalPrecipAmount": 0,
            "totalSnowAmount": 0,
            "windSpeed10m": 3.39,
            "windDirectionFrom10m": 247,
            "windGustSpeed10m": 7.53,
            "visibility": 28417,
            "mslp": 101831,
            "screenRelativeHumidity": 56.68,
            "feelsLikeTemp": 20.97,
            "uvIndex": 0,
            "probOfPrecipitation": 3,
            "probOfSnow": 0,
            "probOfHeavySnow": 0,
            "probOfRain": 3,
            "probOfHeavyRain": 2,
            "probOfHail": 0,
            "probOfSferics": 0
          },
          {
            "time": "2022-06-11T00:00Z",
            "maxScreenAirTemp": 21.94,
            "minScreenAirTemp": 19.35,
            "max10mWindGust": 7.7,
            "significantWeatherCode": 0,
            "totalPrecipAmount": 0,
            "totalSnowAmount": 0,
            "windSpeed10m": 2.8,
            "windDirectionFrom10m": 258,
            "windGustSpeed10m": 5.99,
            "visibility": 27602,
            "mslp": 101855,
            "screenRelativeHumidity": 67.07,
            "feelsLikeTemp": 18.85,
            "uvIndex": 0,
            "probOfPrecipitation": 1,
            "probOfSnow": 0,
            "probOfHeavySnow": 0,
            "probOfRain": 1,
            "probOfHeavyRain": 0,
            "probOfHail": 0,
            "probOfSferics": 0
          },
          {
            "time": "2022-06-11T03:00Z",
            "maxScreenAirTemp": 19.35,
            "minScreenAirTemp": 17.8,
            "max10mWindGust": 6.53,
            "significantWeatherCode": 0,
            "totalPrecipAmount": 0,
            "totalSnowAmount": 0,
            "windSpeed10m": 2.66,
            "windDirectionFrom10m": 275,
            "windGustSpeed10m": 5.75,
            "visibility": 25768,
            "mslp": 101834,
            "screenRelativeHumidity": 73.07,
            "feelsLikeTemp": 17.33,
            "uvIndex": 0,
            "probOfPrecipitation": 2,
            "probOfSnow": 0,
            "probOfHeavySnow": 0,
            "probOfRain": 2,
            "probOfHeavyRain": 1,
            "probOfHail": 0,
            "probOfSferics": 0
          },
          {
            "time": "2022-06-11T06:00Z",
            "maxScreenAirTemp": 17.8,
            "minScreenAirTemp": 16.77,
            "max10mWindGust": 6.65,
            "significantWeatherCode": 3,
            "totalPrecipAmount": 0,
            "totalSnowAmount": 0,
            "windSpeed10m": 2.87,
            "windDirectionFrom10m": 279,
            "windGustSpeed10m": 6.48,
            "visibility": 24817,
            "mslp": 101908,
            "screenRelativeHumidity": 76.05,
            "feelsLikeTemp": 16.29,
            "uvIndex": 1,
            "probOfPrecipitation": 2,
            "probOfSnow": 0,
            "probOfHeavySnow": 0,
            "probOfRain": 2,
            "probOfHeavyRain": 1,
            "probOfHail": 0,
            "probOfSferics": 0
          },
          {
            "time": "2022-06-11T09:00Z",
            "maxScreenAirTemp": 19.33,
            "minScreenAirTemp": 16.92,
            "max10mWindGust": 7.39,
            "significantWeatherCode": 3,
            "totalPrecipAmount": 0,
            "totalSnowAmount": 0,
            "windSpeed10m": 2.99,
            "windDirectionFrom10m": 297,
            "windGustSpeed10m": 7.2,
            "visibility": 27040,
            "mslp": 101919,
            "screenRelativeHumidity": 63.97,
            "feelsLikeTemp": 18.5,
            "uvIndex": 5,
            "probOfPrecipitation": 7,
            "probOfSnow": 0,
            "probOfHeavySnow": 0,
            "probOfRain": 7,
            "probOfHeavyRain": 3,
            "probOfHail": 0,
            "probOfSferics": 1
          },
          {
            "time": "2022-06-11T12:00Z",
            "maxScreenAirTemp": 22.47,
            "minScreenAirTemp": 19.33,
            "max10mWindGust": 8.69,
            "significantWeatherCode": 7,
            "totalPrecipAmount": 0,
            "totalSnowAmount": 0,
            "windSpeed10m": 3.38,
            "windDirectionFrom10m": 270,
            "windGustSpeed10m": 8.63,
            "visibility": 28145,
            "mslp": 101883,
            "screenRelativeHumidity": 50.78,
            "feelsLikeTemp": 21.27,
            "uvIndex": 6,
            "probOfPrecipitation": 7,
            "probOfSnow": 0,
            "probOfHeavySnow": 0,
            "probOfRain": 7,
            "probOfHeavyRain": 2,
            "probOfHail": 0,
            "probOfSferics": 0
          },
          {
            "time": "2022-06-11T15:00Z",
            "maxScreenAirTemp": 23.82,
            "minScreenAirTemp": 22.55,
            "max10mWindGust": 9.72,
            "significantWeatherCode": 3,
            "totalPrecipAmount": 0,
            "totalSnowAmount": 0,
            "windSpeed10m": 3.57,
            "windDirectionFrom10m": 268,
            "windGustSpeed10m": 8.97,
            "visibility": 27685,
            "mslp": 101810,
            "screenRelativeHumidity": 44.67,
            "feelsLikeTemp": 22.36,
            "uvIndex": 3,
            "probOfPrecipitation": 4,
            "probOfSnow": 0,
            "probOfHeavySnow": 0,
            "probOfRain": 4,
            "probOfHeavyRain": 2,
            "probOfHail": 0,
            "probOfSferics": 0
          },
          {
            "time": "2022-06-11T18:00Z",
            "maxScreenAirTemp": 23.76,
            "minScreenAirTemp": 23.25,
            "max10mWindGust": 9.98,
            "significantWeatherCode": 3,
            "totalPrecipAmount": 0,
            "totalSnowAmount": 0,
            "windSpeed10m": 3.47,
            "windDirectionFrom10m": 279,
            "windGustSpeed10m": 8.29,
            "visibility": 26165,
            "mslp": 101757,
            "screenRelativeHumidity": 46.96,
            "feelsLikeTemp": 21.96,
            "uvIndex": 1,
            "probOfPrecipitation": 5,
            "probOfSnow": 0,
            "probOfHeavySnow": 0,
            "probOfRain": 5,
            "probOfHeavyRain": 3,
            "probOfHail": 0,
            "probOfSferics": 1
          }
        ]
      }
    }
  ],
  "parameters": [
    {
      "totalSnowAmount": {
        "type": "Parameter",
        "description": "Total Snow Amount Over Previous Three Hours",
        "unit": {
          "label": "millimetres",
          "symbol": {
            "value": "http://www.opengis.net/def/uom/UCUM/",
            "type": "mm"
          }
        }
      },
      "visibility": {
        "type": "Parameter",
        "description": "Visibility Over Previous Three Hours",
        "unit": {
          "label": "metres",
          "symbol": {
            "value": "http://www.opengis.net/def/uom/UCUM/",
            "type": "m"
          }
        }
      },
      "probOfHail": {
        "type": "Parameter",
        "description": "Three Hour Probability of Hail",
        "unit": {
          "label": "percentage",
          "symbol": {
            "value": "http://www.opengis.net/def/uom/UCUM/",
            "type": "%"
          }
        }
      },
      "windDirectionFrom10m": {
        "type": "Parameter",
        "description": "10m Wind From Direction Over Previous Three Hours",
        "unit": {
          "label": "degrees",
          "symbol": {
            "value": "http://www.opengis.net/def/uom/UCUM/",
            "type": "deg"
          }
        }
      },
      "probOfHeavyRain": {
        "type": "Parameter",
        "description": "Three Hour Probability of Heavy Rain",
        "unit": {
          "label": "percentage",
          "symbol": {
            "value": "http://www.opengis.net/def/uom/UCUM/",
            "type": "%"
          }
        }
      },
      "maxScreenAirTemp": {
        "type": "Parameter",
        "description": "Maximum Screen Air Temperature Over Previous Three Hours",
        "unit": {
          "label": "degrees Celsius",
          "symbol": {
            "value": "http://www.opengis.net/def/uom/UCUM/",
            "type": "Cel"
          }
        }
      },
      "feelsLikeTemp": {
        "type": "Parameter",
        "description": "Feels Like Temperature Over Previous Three Hours",
        "unit": {
          "label": "degrees Celsius",
          "symbol": {
            "value": "http://www.opengis.net/def/uom/UCUM/",
            "type": "Cel"
          }
        }
      },
      "probOfSferics": {
        "type": "Parameter",
        "description": "Three Hour Probability of Sferics",
        "unit": {
          "label": "percentage",
          "symbol": {
            "value": "http://www.opengis.net/def/uom/UCUM/",
            "type": "%"
          }
        }
      },
      "screenRelativeHumidity": {
        "type": "Parameter",
        "description": "Screen Relative Humidity Over Previous Three Hours",
        "unit": {
          "label": "percentage",
          "symbol": {
            "value": "http://www.opengis.net/def/uom/UCUM/",
            "type": "%"
          }
        }
      },
      "windSpeed10m": {
        "type": "Parameter",
        "description": "10m Wind Speed Over Previous Three Hours",
        "unit": {
          "label": "metres per second",
          "symbol": {
            "value": "http://www.opengis.net/def/uom/UCUM/",
            "type": "m/s"
          }
        }
      },
      "probOfPrecipitation": {
        "type": "Parameter",
        "description": "Three Hour Probability of Precipitation",
        "unit": {
          "label": "percentage",
          "symbol": {
            "value": "http://www.opengis.net/def/uom/UCUM/",
            "type": "%"
          }
        }
      },
      "probOfRain": {
        "type": "Parameter",
        "description": "Three Hour Probability of Rain",
        "unit": {
          "label": "percentage",
          "symbol": {
            "value": "http://www.opengis.net/def/uom/UCUM/",
            "type": "%"
          }
        }
      },
      "max10mWindGust": {
        "type": "Parameter",
        "description": "Maximum 10m Wind Gust Speed Over Previous Three Hours",
        "unit": {
          "label": "metres per second",
          "symbol": {
            "value": "http://www.opengis.net/def/uom/UCUM/",
            "type": "m/s"
          }
        }
      },
      "significantWeatherCode": {
        "type": "Parameter",
        "description": "Three Hour Significant Weather Code",
        "unit": {
          "label": "dimensionless",
          "symbol": {
            "value": "https://metoffice.apiconnect.ibmcloud.com/metoffice/production/",
            "type": "1"
          }
        }
      },
      "probOfHeavySnow": {
        "type": "Parameter",
        "description": "Three Hour Probability of Heavy Snow",
        "unit": {
          "label": "percentage",
          "symbol": {
            "value": "http://www.opengis.net/def/uom/UCUM/",
            "type": "%"
          }
        }
      },
      "minScreenAirTemp": {
        "type": "Parameter",
        "description": "Minimum Screen Air Temperature Over Previous Three Hours",
        "unit": {
          "label": "degrees Celsius",
          "symbol": {
            "value": "http://www.opengis.net/def/uom/UCUM/",
            "type": "Cel"
          }
        }
      },
      "totalPrecipAmount": {
        "type": "Parameter",
        "description": "Total Precipitation Amount Over Previous Three Hours",
        "unit": {
          "label": "millimetres",
          "symbol": {
            "value": "http://www.opengis.net/def/uom/UCUM/",
            "type": "mm"
          }
        }
      },
      "mslp": {
        "type": "Parameter",
        "description": "Mean Sea Level Pressure Over Previous Three Hours",
        "unit": {
          "label": "pascals",
          "symbol": {
            "value": "http://www.opengis.net/def/uom/UCUM/",
            "type": "Pa"
          }
        }
      },
      "windGustSpeed10m": {
        "type": "Parameter",
        "description": "10m Wind Gust Speed Over Previous Three Hours",
        "unit": {
          "label": "metres per second",
          "symbol": {
            "value": "http://www.opengis.net/def/uom/UCUM/",
            "type": "m/s"
          }
        }
      },
      "uvIndex": {
        "type": "Parameter",
        "description": "Maximum UV Index Over Previous Three Hours",
        "unit": {
          "label": "dimensionless",
          "symbol": {
            "value": "http://www.opengis.net/def/uom/UCUM/",
            "type": "1"
          }
        }
      },
      "probOfSnow": {
        "type": "Parameter",
        "description": "Three Hour Probability of Snow",
        "unit": {
          "label": "percentage",
          "symbol": {
            "value": "http://www.opengis.net/def/uom/UCUM/",
            "type": "%"
          }
        }
      }
    }
  ]
}
